thaicovid19/__init__.py
thaicovid19-0.0.1.dist-info/LICENSE
thaicovid19-0.0.1.dist-info/METADATA
thaicovid19-0.0.1.dist-info/WHEEL
thaicovid19-0.0.1.dist-info/top_level.txt
thaicovid19-0.0.1.dist-info/RECORD
